dpsearchclient/__init__.py
dpsearchclient/meta_data.py
dpsearchclient/search_client.py
dpsearchclient/search_engine.py
dpssearchclient-1.0.0.dist-info/METADATA
dpssearchclient-1.0.0.dist-info/WHEEL
dpssearchclient-1.0.0.dist-info/top_level.txt
dpssearchclient-1.0.0.dist-info/RECORD
