Metadata-Version: 2.1
Name: dpssearchclient
Version: 1.0.0
Summary: UNKNOWN
Home-page: https://github.com/TinDang97/DPS_SearchEngine_Client
Author: TinDang
Author-email: rainstone1029x@gmail.com
License: MIT
Platform: UNKNOWN
Requires-Dist: dpsutil (>=1.1.13)
Requires-Dist: numpy
